{"groups":[{"keys":"b1_png,b2_png,bg_jpg,bloodBar_png,bloodBarBg_png,boss_png,btn_start_png,buff_blood_png,enemyBullet_png,f1_png,f2_png,hp_png,restart_png,bomb_mp3,readygo_mp3,bgm_mp3,bomb2_mp3,bgm2_mp3,readygo2_mp3,F_Mofageji_ske_json,F_Mofageji_tex_json,F_Mofageji_tex_png,F_Lieyanwangzi_ske_json,F_Lieyanwangzi_tex_json,F_Lieyanwangzi_tex_png,F_Shuijingshinv_ske_json,F_Shuijingshinv_tex_json,F_Shuijingshinv_tex_png,F_zhanshen20_ske_json,F_zhanshen20_tex_json,F_zhanshen20_tex_png","name":"preload"}],"resources":[{"url":"config/description.json","type":"json","name":"description_json"},{"url":"assets/sound/bomb_4ecd2932.mp3","type":"sound","name":"bomb_mp3"},{"url":"assets/sound/readygo_eef94f0.mp3","type":"sound","name":"readygo_mp3"},{"url":"assets/sound/bgm_427688c0.mp3","type":"sound","name":"bgm_mp3"},{"url":"assets/sound/bomb_4ecd2932.mp3","type":"sound","name":"bomb2_mp3"},{"url":"assets/sound/bgm_427688c0.mp3","type":"sound","name":"bgm2_mp3"},{"url":"assets/sound/readygo_eef94f0.mp3","type":"sound","name":"readygo2_mp3"},{"url":"assets/F_Mofageji/F_Mofageji_ske_1971e928.json","type":"json","name":"F_Mofageji_ske_json"},{"url":"assets/F_Mofageji/F_Mofageji_tex_38374eb8.json","type":"json","name":"F_Mofageji_tex_json"},{"url":"assets/F_Mofageji/F_Mofageji_tex_41bf7cd7.png","type":"image","name":"F_Mofageji_tex_png"},{"url":"assets/F_Lieyanwangzi/F_Lieyanwangzi_ske_1471e6ab.json","type":"json","name":"F_Lieyanwangzi_ske_json"},{"url":"assets/F_Lieyanwangzi/F_Lieyanwangzi_tex_2dd5434a.json","type":"json","name":"F_Lieyanwangzi_tex_json"},{"url":"assets/F_Lieyanwangzi/F_Lieyanwangzi_tex_6d87eeaa.png","type":"image","name":"F_Lieyanwangzi_tex_png"},{"url":"assets/F_Shuijingshinv/F_Shuijingshinv_ske_a9f2217.json","type":"json","name":"F_Shuijingshinv_ske_json"},{"url":"assets/F_Shuijingshinv/F_Shuijingshinv_tex_69b5645c.json","type":"json","name":"F_Shuijingshinv_tex_json"},{"url":"assets/F_Shuijingshinv/F_Shuijingshinv_tex_7db95ea5.png","type":"image","name":"F_Shuijingshinv_tex_png"},{"url":"assets/F_zhanshen20/F_zhanshen20_ske_58a041d8.json","type":"json","name":"F_zhanshen20_ske_json"},{"url":"assets/F_zhanshen20/F_zhanshen20_tex_64ac04a8.json","type":"json","name":"F_zhanshen20_tex_json"},{"url":"assets/F_zhanshen20/F_zhanshen20_tex_bf89770.png","type":"image","name":"F_zhanshen20_tex_png"},{"url":"packs0/preload-0sheet_4b6d3bd4.json","type":"sheet","name":"preload-0sheet","subkeys":"restart_png,hp_png,f2_png,f1_png,enemyBullet_png,buff_blood_png,btn_start_png,boss_png,bloodBar_png,bloodBarBg_png,bg_jpg,b2_png,b1_png"}]}